{
 "SoundBanksInfo": {
  "Platform": "Mac",
  "BasePlatform": "Mac",
  "SchemaVersion": "16",
  "SoundBankVersion": "154",
  "SoundBanks": [
   {
    "Id": "2607556080",
    "Type": "Event",
    "GUID": "{EFD9D6BA-A2FB-4BE4-9A37-E9F86430AA63}",
    "Language": "SFX",
    "Hash": "{07A51E5B-C5BC-8BFD-AD89-2B62913D1DFF}",
    "ObjectPath": "Menu",
    "ShortName": "Menu",
    "Path": "Event/Menu.bnk",
    "Media": [
     {
      "Id": "696858604",
      "Language": "SFX",
      "Streaming": "false",
      "Location": "Loose",
      "ShortName": "MX_MENU\\MX_MENU.wav",
      "Path": "Media/696858604.wem",
      "CachePath": "56/{566083CE-764E-01F8-31F1-6D5855763635}.wem"
     },
     {
      "Id": "891888299",
      "Language": "SFX",
      "Streaming": "false",
      "Location": "Loose",
      "ShortName": "MX_STING_LIGHTBULB\\MX_STING_LIGHTBULBzzFullMix.wav",
      "Path": "Media/891888299.wem",
      "CachePath": "FD/{FD12FA6A-430C-E99A-F189-81226074ECDE}.wem"
     }
    ],
    "Plugins": {
     "ShareSets": [
      {
       "Id": "1008402193",
       "Name": "Low_Pass_20KHz",
       "ObjectPath": "\\Effects\\Factory Effects\\Parametric EQ\\Low Pass Filters\\Low_Pass_20KHz",
       "GUID": "{830124FB-B9D5-4AE8-846E-E94A74652666}",
       "LibName": "Wwise Parametric EQ",
       "LibId": "6881283"
      }
     ]
    },
    "Events": [
     {
      "Id": "2607556080",
      "Name": "Menu",
      "ObjectPath": "\\Events\\MUSIC\\Menu",
      "GUID": "{EFD9D6BA-A2FB-4BE4-9A37-E9F86430AA63}",
      "DurationType": "OneShot",
      "DurationMin": "121.42587",
      "DurationMax": "121.42587",
      "MediaRefs": [
       {
        "Id": "696858604"
       },
       {
        "Id": "891888299"
       }
      ],
      "PluginRefs": {
       "ShareSets": [
        {
         "Id": "1008402193"
        }
       ]
      }
     }
    ],
    "Triggers": [
     {
      "Id": "2031596562",
      "Name": "Lightbulb",
      "ObjectPath": "\\Triggers\\Music\\Lightbulb",
      "GUID": "{81B271F5-95A0-421D-B40B-99460F92B8ED}"
     }
    ]
   }
  ],
  "FileHash": "{BDE26B0D-BE74-2644-DE69-96BE5DFEC047}"
 }
}